pytest_depends/__init__.py
pytest_depends/constants.py
pytest_depends/main.py
pytest_depends/util.py
pytest_depends-1.0.1.dist-info/LICENSE
pytest_depends-1.0.1.dist-info/METADATA
pytest_depends-1.0.1.dist-info/WHEEL
pytest_depends-1.0.1.dist-info/entry_points.txt
pytest_depends-1.0.1.dist-info/top_level.txt
pytest_depends-1.0.1.dist-info/RECORD
